<?xml version="1.0" encoding="UTF-8" standalone="no"?>
<!DOCTYPE properties SYSTEM "http://java.sun.com/dtd/properties.dtd">
<properties>
    <entry key="app_title">RedisFx</entry>
    <entry key="confirm_delete_key">确定要删除指定的 KEY 吗？</entry>
    <entry key="dlg_conn_lbl_connections">连接</entry>
    <entry key="dlg_conn_lbl_host">主机：</entry>
    <entry key="dlg_conn_lbl_name">名称：</entry>
    <entry key="dlg_conn_lbl_pass">密码（可选）：</entry>
    <entry key="dlg_conn_lbl_port">端口：</entry>
    <entry key="empty_mark">（空）</entry>
    <entry key="mnu_connections">连接</entry>
    <entry key="mnu_connections_choose">选择连接...</entry>
    <entry key="mnu_connections_recent">打开最近的连接...</entry>
    <entry key="op_open_conn">打开连接</entry>
    <entry key="op_copy">复制</entry>
    <entry key="op_delete">删除</entry>
    <entry key="op_save">保存</entry>
    <entry key="op_increase">加一</entry>
    <entry key="op_decrease">减一</entry>
    <entry key="tab_title_geo">Geo</entry>
    <entry key="tab_title_hash">Hash</entry>
    <entry key="tab_title_key">Key</entry>
    <entry key="tab_title_list">List</entry>
    <entry key="tab_title_pubsub">Pub/Sub</entry>
    <entry key="tab_title_raw">命令行</entry>
    <entry key="tab_title_set">Set</entry>
    <entry key="tab_title_string">String</entry>
    <entry key="tab_title_zset">ZSet</entry>
    <entry key="title_conn_manager">连接管理</entry>
    <entry key="title_op_fail">操作失败</entry>
    <entry key="op_close">关闭</entry>
    <entry key="op_create">新建</entry>
    <entry key="msg_please_create_connection">（请在右边新建一个连接）</entry>
    <entry key="msg_create_confirm">清空现有内容并新建连接吗？</entry>
    <entry key="msg_delete_confirm">确定要删除该连接吗？</entry>
    <entry key="op_test">测试...</entry>
</properties>